django_celery_fsm/__init__.py
django_celery_fsm/discovery.py
django_celery_fsm/fsm.py
django_celery_fsm/models.py
django_celery_fsm/tasks.py
django_celery_fsm-0.0.1.dist-info/LICENSE
django_celery_fsm-0.0.1.dist-info/METADATA
django_celery_fsm-0.0.1.dist-info/WHEEL
django_celery_fsm-0.0.1.dist-info/top_level.txt
django_celery_fsm-0.0.1.dist-info/RECORD
