Metadata-Version: 2.1
Name: django-celery-fsm
Version: 0.0.1
Summary: Django FSM with Celery tasks as step handler
Home-page: https://github.com/slivetssergey/django-celery-fsm
Author: Sergey Slivets
Author-email: slivetssergey@gmail.com
License: License :: OSI Approved :: MIT License
Keywords: django-celery-fsm
Classifier: Development Status :: 2 - Pre-Alpha
Classifier: Intended Audience :: Developers
Classifier: License :: OSI Approved :: MIT License
Classifier: Natural Language :: English
Classifier: Programming Language :: Python :: 3
Classifier: Programming Language :: Python :: 3.7
Classifier: Programming Language :: Python :: 3.8
Classifier: Programming Language :: Python :: 3.9
Requires-Python: >=3.7
License-File: LICENSE
